litestar_mcp/__init__.py
litestar_mcp/__metadata__.py
litestar_mcp/_typing.py
litestar_mcp/cli.py
litestar_mcp/config.py
litestar_mcp/decorators.py
litestar_mcp/executor.py
litestar_mcp/plugin.py
litestar_mcp/py.typed
litestar_mcp/routes.py
litestar_mcp/schema.py
litestar_mcp/schema_builder.py
litestar_mcp/typing.py
litestar_mcp/utils.py
litestar_mcp-0.2.2.dist-info/METADATA
litestar_mcp-0.2.2.dist-info/WHEEL
litestar_mcp-0.2.2.dist-info/licenses/LICENSE
litestar_mcp-0.2.2.dist-info/RECORD
