Metadata-Version: 2.4
Name: litestar-mcp
Version: 0.2.2
Summary: Litestar plugin for Model Context Protocol (MCP) integration
Project-URL: Changelog, https://docs.litestar-mcp.litestar.dev/latest/changelog
Project-URL: Discord, https://discord.gg/litestar
Project-URL: Documentation, https://docs.litestar-mcp.litestar.dev/latest/
Project-URL: Funding, https://github.com/sponsors/litestar-org
Project-URL: Homepage, https://docs.litestar-mcp.litestar.dev/latest/
Project-URL: Issue, https://github.com/litestar-org/litestar-mcp/issues/
Project-URL: Source, https://github.com/litestar-org/litestar-mcp
Author-email: Cody Fincher <cody@litestar.dev>
Maintainer-email: Litestar Developers <hello@litestar.dev>, Cody Fincher <cody@litestar.dev>
License: MIT
License-File: LICENSE
Keywords: ai,litestar,mcp,model-context-protocol,plugin
Classifier: Development Status :: 4 - Beta
Classifier: Environment :: Web Environment
Classifier: Intended Audience :: Developers
Classifier: Intended Audience :: System Administrators
Classifier: License :: OSI Approved :: MIT License
Classifier: Natural Language :: English
Classifier: Operating System :: OS Independent
Classifier: Programming Language :: Python
Classifier: Programming Language :: Python :: 3.9
Classifier: Programming Language :: Python :: 3.10
Classifier: Programming Language :: Python :: 3.11
Classifier: Programming Language :: Python :: 3.12
Classifier: Programming Language :: Python :: 3.13
Classifier: Topic :: Internet :: WWW/HTTP :: Dynamic Content
Classifier: Topic :: Scientific/Engineering :: Artificial Intelligence
Classifier: Topic :: Software Development
Classifier: Topic :: Software Development :: Libraries :: Application Frameworks
Classifier: Typing :: Typed
Requires-Python: >=3.9
Requires-Dist: click>=8.0.0
Requires-Dist: eval-type-backport; python_full_version < '3.10'
Requires-Dist: litestar>=2.0.0
Requires-Dist: rich>=13.0.0
Requires-Dist: typing-extensions>=4.0.0
